linq/__init__.py
linq/_query.py
linq/_distributed_query/__init__.py
linq/_distributed_query/feeder.py
linq/_distributed_query/task_tracker.py
linq/_distributed_query/worker.py
linq/_distributed_query/yielder.py
linq/_distributed_query/query/__init__.py
linq/_distributed_query/query/aggregators.py
linq/_distributed_query/query/executor.py
linq/_distributed_query/query/blocks/__init__.py
linq/_distributed_query/query/blocks/base.py
linq/_distributed_query/query/blocks/flatten.py
linq/_distributed_query/query/blocks/select.py
linq/_distributed_query/query/blocks/where.py
linq/errors/__init__.py
linq/errors/_no_such_element_error.py
python_linq-2.0.4.dist-info/LICENSE
python_linq-2.0.4.dist-info/METADATA
python_linq-2.0.4.dist-info/WHEEL
python_linq-2.0.4.dist-info/top_level.txt
python_linq-2.0.4.dist-info/RECORD
