Metadata-Version: 2.1
Name: python-linq
Version: 2.0.4
Summary: Brings LINQ to Python
Home-page: https://github.com/jakkes/python-linq
Author: Jakob Stigenberg
License: UNKNOWN
Platform: UNKNOWN
Classifier: Programming Language :: Python :: 3
Classifier: License :: OSI Approved :: MIT License
Classifier: Operating System :: OS Independent
Requires-Python: >=3.7
